gptswe/__init__.py
gptswe/gptswe.py
gptswe-1.2.4.dist-info/LICENSE
gptswe-1.2.4.dist-info/METADATA
gptswe-1.2.4.dist-info/WHEEL
gptswe-1.2.4.dist-info/entry_points.txt
gptswe-1.2.4.dist-info/top_level.txt
gptswe-1.2.4.dist-info/RECORD
